businesstimedelta/__init__.py
businesstimedelta/businesstimedelta.py
businesstimedelta/rules/__init__.py
businesstimedelta/rules/holidayrules.py
businesstimedelta/rules/rule.py
businesstimedelta/rules/rules.py
businesstimedelta/rules/workdayrules.py
businesstimedelta-1.0.1.dist-info/LICENSE.txt
businesstimedelta-1.0.1.dist-info/METADATA
businesstimedelta-1.0.1.dist-info/WHEEL
businesstimedelta-1.0.1.dist-info/top_level.txt
businesstimedelta-1.0.1.dist-info/RECORD
