Metadata-Version: 2.1
Name: businesstimedelta
Version: 1.0.1
Summary: Timedelta for business time. Supports exact amounts of time (hours, seconds), custom schedules, holidays, and time zones.
Home-page: http://github.com/seppemans/businesstimedelta
Author: seppemans
License: MIT
Keywords: business working time timedelta hours businesstime businesshours
Platform: UNKNOWN
Classifier: Development Status :: 5 - Production/Stable
Classifier: License :: OSI Approved :: MIT License
Classifier: Programming Language :: Python :: 2.7
Classifier: Programming Language :: Python :: 3.4
Classifier: Programming Language :: Python :: 3.5
Classifier: Programming Language :: Python :: 3.6
Classifier: Programming Language :: Python :: 3.7
Classifier: Topic :: Office/Business :: Scheduling
